pineworkslabs/GPIO.py
pineworkslabs/RPi.py
pineworkslabs/__init__.py
pineworkslabs-0.2.0.dist-info/LICENSE
pineworkslabs-0.2.0.dist-info/METADATA
pineworkslabs-0.2.0.dist-info/WHEEL
pineworkslabs-0.2.0.dist-info/top_level.txt
pineworkslabs-0.2.0.dist-info/RECORD
