Metadata-Version: 2.1
Name: pineworkslabs
Version: 0.2.0
Summary: An access layer for the Pineworks Labs RP2040 GPIO board
Home-page: https://gitlab.com/pineworkslabs/rp-2040-gpio-board
Author: Pineworks Labs
Author-email: shelby@pineworkslabs.com
Project-URL: Bug Tracker, https://gitlab.com/pineworkslabs/rp-2040-gpio-board/-/issues
Classifier: Programming Language :: Python :: 3
Classifier: License :: OSI Approved :: MIT License
Classifier: Operating System :: OS Independent
Requires-Python: >=3.7
License-File: LICENSE
